fortmatic/__init__.py
fortmatic/config.py
fortmatic/errors.py
fortmatic/api_resources/__init__.py
fortmatic/api_resources/config.py
fortmatic/api_resources/auth/__init__.py
fortmatic/api_resources/auth/resource_uris.py
fortmatic/api_resources/auth/user.py
fortmatic/api_resources/util/__init__.py
fortmatic/api_resources/util/exceptions.py
fortmatic/api_resources/util/request_helpers.py
fortmatic/django/__init__.py
fortmatic/django/config.py
fortmatic/django/exceptions.py
fortmatic/django/utils.py
fortmatic/django/auth/__init__.py
fortmatic/django/auth/backends.py
fortmatic/django/auth/middleware.py
fortmatic/django/auth/models.py
fortmatic/utils/__init__.py
fortmatic/utils/auth.py
fortmatic/utils/http.py
fortmatic/utils/logging.py
fortmatic/utils/time.py
fortmatic-0.0.7.dist-info/LICENSE.txt
fortmatic-0.0.7.dist-info/METADATA
fortmatic-0.0.7.dist-info/WHEEL
fortmatic-0.0.7.dist-info/top_level.txt
fortmatic-0.0.7.dist-info/RECORD
