Metadata-Version: 2.1
Name: fortmatic
Version: 0.0.7
Summary: Fortmatic Python Library
Home-page: https://fortmatic.com
Author: Fortmatic
Author-email: support@fortmatic.com
License: MIT
Project-URL: Website, https://fortmatic.com
Keywords: fortmatic python sdk
Platform: UNKNOWN
Classifier: Development Status :: 3 - Alpha
Classifier: Programming Language :: Python
Classifier: Programming Language :: Python :: 3.6
Classifier: Intended Audience :: Developers
Classifier: License :: OSI Approved :: MIT License
Classifier: Operating System :: OS Independent
Requires-Python: >=3.6
Requires-Dist: requests (==2.22)
Requires-Dist: web3 (==5.4.0)
Requires-Dist: retrying (==1.3.3)
